LICENSE
MANIFEST.in
README.md
setup.py
pretty_exception.egg-info/PKG-INFO
pretty_exception.egg-info/SOURCES.txt
pretty_exception.egg-info/dependency_links.txt
pretty_exception.egg-info/top_level.txt
prettyexc/__init__.py
prettyexc/environment.py
prettyexc/tests.py
prettyexc/version.txt