Metadata-Version: 1.0
Name: pretty-exception
Version: 0.1
Summary: Easy pretty-look exception interface.
Home-page: https://github.com/youknowone/pretty-exception
Author: Jeong YunWon
Author-email: jeong+prettyexc@youknowone.org
License: UNKNOWN
Platform: UNKNOWN
